{"title":"书有可浅尝者，有可吞食者，少数则须咀嚼消化","slug":"欣赏一下壁纸","date":"2017-03-28T09:19:30.000Z","updated":"2017-03-28T09:44:34.000Z","comments":true,"path":"api/articles/欣赏一下壁纸.json","excerpt":"","content":"<blockquote>\n<p>Some books are to be tasted, others to be swallowed, and some few to be chewed and digested; that is, some books are to be read only in parts; others to be read, but not curiously; and some few to be read wholly, and with diligence and attention. 书有可浅尝者，有可吞食者，少数则须咀嚼消化。换言之，有只须读其部分者，有只须大体涉猎者，少数则须全读，读时须全神贯注，孜孜不倦。   —培根《论读书》</p>\n</blockquote>\n<p><img src=\"https://server-19860911.oss-cn-beijing.aliyuncs.com/hexoResource/1490692802051/images/pasted-0.png\" alt=\"upload successful\"></p>\n<p><img src=\"https://server-19860911.oss-cn-beijing.aliyuncs.com/hexoResource/1490692811098/images/pasted-0.png\" alt=\"upload successful\"></p>\n","categories":[],"tags":[]}